Sicp2eMit6001/README.md
Sicp2eMit6001/__init__.py
Sicp2eMit6001/__main__.py
Sicp2eMit6001/file.epub
Sicp2eMit6001/index.html
Sicp2eMit6001/css/__init__.py
Sicp2eMit6001/css/annotations.css
Sicp2eMit6001/css/main.css
Sicp2eMit6001/css/normalize.css
Sicp2eMit6001/css/popup.css
Sicp2eMit6001/font/__init__.py
Sicp2eMit6001/font/fontello.eot
Sicp2eMit6001/font/fontello.svg
Sicp2eMit6001/font/fontello.ttf
Sicp2eMit6001/font/fontello.woff
Sicp2eMit6001/img/__init__.py
Sicp2eMit6001/img/annotator-glyph-sprite.png
Sicp2eMit6001/img/annotator-icon-sprite.png
Sicp2eMit6001/img/apple-touch-icon.png
Sicp2eMit6001/img/cancelfullscreen.png
Sicp2eMit6001/img/close.png
Sicp2eMit6001/img/fullscreen.png
Sicp2eMit6001/img/loader.gif
Sicp2eMit6001/img/menu-icon.png
Sicp2eMit6001/img/save.png
Sicp2eMit6001/img/saved.png
Sicp2eMit6001/img/settings-s.png
Sicp2eMit6001/img/settings.png
Sicp2eMit6001/img/star.png
Sicp2eMit6001/js/__init__.py
Sicp2eMit6001/js/epub.js
Sicp2eMit6001/js/epub.min.js
Sicp2eMit6001/js/epub.min.map
Sicp2eMit6001/js/hooks.min.js
Sicp2eMit6001/js/hooks.min.map
Sicp2eMit6001/js/reader.js
Sicp2eMit6001/js/reader.js.map
Sicp2eMit6001/js/reader.min.js
Sicp2eMit6001/js/reader.min.map
Sicp2eMit6001/js/hooks/__init__.py
Sicp2eMit6001/js/hooks/extensions/__init__.py
Sicp2eMit6001/js/hooks/extensions/highlight.js
Sicp2eMit6001/js/libs/__init__.py
Sicp2eMit6001/js/libs/jquery.min.js
Sicp2eMit6001/js/libs/localforage.min.js
Sicp2eMit6001/js/libs/screenfull.js
Sicp2eMit6001/js/libs/screenfull.min.js
Sicp2eMit6001/js/libs/zip.min.js
Sicp2eMit6001/js/plugins/__init__.py
Sicp2eMit6001/js/plugins/hypothesis.js
Sicp2eMit6001/js/plugins/search.js
sicp_2e_mit_6_001-2024.3.2.0.dist-info/METADATA
sicp_2e_mit_6_001-2024.3.2.0.dist-info/WHEEL
sicp_2e_mit_6_001-2024.3.2.0.dist-info/entry_points.txt
sicp_2e_mit_6_001-2024.3.2.0.dist-info/top_level.txt
sicp_2e_mit_6_001-2024.3.2.0.dist-info/RECORD
